README.rst
setup.py
berlioz/__init__.py
berlioz/aws.py
berlioz/client.py
berlioz/cluster.py
berlioz/deep_eq.py
berlioz/environment.py
berlioz/executor.py
berlioz/http_peer_accessor.py
berlioz/log.py
berlioz/metadata.py
berlioz/native_resource.py
berlioz/peer_accessor.py
berlioz/peer_helper.py
berlioz/policy.py
berlioz/processor.py
berlioz/registry.py
berlioz/secret.py
berlioz/sector.py
berlioz/service.py
berlioz/starter.py
berlioz/utils.py
berlioz/zipkin.py
berlioz.egg-info/PKG-INFO
berlioz.egg-info/SOURCES.txt
berlioz.egg-info/dependency_links.txt
berlioz.egg-info/requires.txt
berlioz.egg-info/top_level.txt
berlioz/frameworks/__init__.py
berlioz/frameworks/b_flask.py
berlioz/frameworks/__init__.py
berlioz/frameworks/b_flask.py