Metadata-Version: 1.2
Name: berlioz
Version: 0.1.22
Summary: Python SDK for Berlioz Cloud
Home-page: https://berlioz.cloud
Author: Berlioz
Author-email: info@berlioz.cloud
Maintainer: Ruben Hakopian
Maintainer-email: ruben@berlioz.cloud
License: Apache License 2.0
Keywords: microservices service mesh cloud aws
Platform: any
Classifier: Development Status :: 3 - Alpha
Classifier: Environment :: Web Environment
Classifier: Framework :: Flask
Classifier: License :: OSI Approved :: Apache Software License
Classifier: Programming Language :: Python
Classifier: Programming Language :: Python :: 2
Classifier: Programming Language :: Python :: 2.7
Classifier: Programming Language :: Python :: 3
Classifier: Programming Language :: Python :: 3.6
Classifier: Topic :: Internet :: WWW/HTTP
Classifier: Topic :: Software Development :: Libraries
Classifier: Topic :: Software Development :: Libraries :: Application Frameworks
Classifier: Topic :: Software Development :: Libraries :: Python Modules
Classifier: Topic :: System :: Monitoring
Requires-Python: >=2.7,!=3.0.*,!=3.1.*,!=3.2.*,!=3.3.*
